simil/__init__.py
simil/__main__.py
simil/cli_args.py
simil/client.py
simil/server.py
simil/version.py
simil-0.0.2.dist-info/LICENSE
simil-0.0.2.dist-info/METADATA
simil-0.0.2.dist-info/WHEEL
simil-0.0.2.dist-info/entry_points.txt
simil-0.0.2.dist-info/top_level.txt
simil-0.0.2.dist-info/RECORD
