Metadata-Version: 2.1
Name: simil
Version: 0.0.2
Summary: CLI for semantic string similarity
Home-page: https://github.com/foxbenjaminfox/string-similarity-cli
Author: Benjamin Fox
Author-email: foxbenjaminfox@gmail.com
License: UNKNOWN
Platform: UNKNOWN
Classifier: Programming Language :: Python :: 3
Classifier: License :: OSI Approved :: GNU General Public License v3 (GPLv3)
Requires-Dist: rpyc
Requires-Dist: spacy
